{
  "contacts": [
    {
      "id": "123456",
      "nombre": "Jose",
      "apellido": "Linero",
      "cargo": "Senior Collaboration SE",
      "email": "jlinero@cisco.com",
      "email2": "",
      "telefono": "+573102634216",
      "empresa": "Cisco",
      "dominioEmpresa": "",
      "telEmpresa": "+576013256052",
      "ciudad": "Bogotá, Colombia",
      "etapaVida": "cliente",
      "estadoLead": "Nuevo",
      "propietarioContacto": "",
      "zonaHoraria": "America/Bogota",
      "objetivoMarketing": "",
      "presupuesto": "",
      "timeline": "",
      "notas": "",
      "actividades": [
        {
          "id": "mod2bgldp1d",
          "tipo": "email",
          "descripcion": "El cliente escribió un correo manifestando interes en Webex Calling",
          "asignadoA": "Oscar Piastri",
          "fecha": "2026-04-24T15:25:40.417Z"
        },
        {
          "id": "1776996900745",
          "tipo": "whatsapp",
          "descripcion": "El cliente se comunicó para preguntar por el estado de sus casos abiertos, no se ha tenido avance en ninguno, se le estará comunicando cuando se tengan avances",
          "asignadoA": "Lando Norris",
          "fecha": "2026-04-24T02:15:00.745Z"
        },
        {
          "id": "1776994507908",
          "tipo": "llamada",
          "descripcion": "El cliente, que está construyendo un edificio en Medellín, se contactó para conocer los productos y tipos de cemento disponibles (incluyendo opciones sostenibles) y confirmar detalles de un pedido de 1000 bultos. Durante la atención se brindó información, se verificó el pedido en el sistema, se reprogramó la entrega para el 27 de abril y también se solicitó adelantarla; además, se envió la confirmación por correo y se acordó enviar más información y conectar al cliente con un asesor humano",
          "asignadoA": "Lando Norris",
          "fecha": "2026-04-24T01:35:07.908Z"
        },
        {
          "id": "1776983282507",
          "tipo": "whatsapp",
          "descripcion": "El cliente tiene interés en el servicio de Webex Contact Center",
          "asignadoA": "Oscar Piastri",
          "fecha": "2026-04-23T22:28:02.507Z"
        },
        {
          "id": "1776982642399",
          "tipo": "llamada",
          "descripcion": "El cliente tiene interés en el servicio de Webex Contact Center",
          "asignadoA": "Oscar Piastri",
          "fecha": "2026-04-23T22:17:22.399Z"
        },
        {
          "id": "mobq02qroql",
          "tipo": "email",
          "descripcion": "El cliente escribió un correo manifestando interes en Webex Calling",
          "asignadoA": "Oscar Piastri",
          "fecha": "2026-04-23T16:53:07.683Z"
        },
        {
          "id": "moaju9bbrk4",
          "tipo": "email",
          "descripcion": "El cliente escribió un correo manifestando interes en Webex Calling",
          "asignadoA": "Oscar Piastri",
          "fecha": "2026-04-22T21:12:52.391Z"
        },
        {
          "id": "moajoa9yp0v",
          "tipo": "llamada",
          "descripcion": "El cliente llamó con interés en Webex Contact Center",
          "asignadoA": "Lando Norris",
          "fecha": "2026-04-22T21:08:13.702Z"
        },
        {
          "id": "moaghznb1hhktni091j",
          "tipo": "llamada",
          "descripcion": "El cliente esta interesado en la solución de Webex Contact Center",
          "fecha": "2026-04-22T19:39:21.143Z"
        }
      ],
      "deals": [
        {
          "id": "moc59bb1py0jkgv9x8",
          "nombre": "Webex Calling",
          "monto": "$20,000",
          "fechaCierre": "Julio 30, 2026",
          "etapa": "Calificado",
          "creadoEn": "2026-04-24T00:00:12.925Z"
        }
      ],
      "tickets": [
        {
          "id": "526284",
          "numero": "526284",
          "nombre": "Agente no puede cambiar de estado en Contact Center",
          "estado": "en progreso",
          "creadoEn": "2026-04-24T22:03:32.272Z",
          "actualizaciones": [
            {
              "id": "modia9mwrhxazkwawn",
              "nota": "se esta haciendo una revisión inicial del caso",
              "agente": "Lando Norris",
              "fecha": "2026-04-24T22:52:38.600Z",
              "estadoAnterior": "abierto",
              "estadoNuevo": "en progreso"
            },
            {
              "id": "1777068212272",
              "nota": "El usuario reporta que cuando el agente está logueado no puede hacer el cambio de estado, lo que impide recibir llamadas o interacciones digitales.",
              "agente": "Sistema",
              "fecha": "2026-04-24T22:03:32.272Z",
              "estadoAnterior": "",
              "estadoNuevo": ""
            }
          ],
          "actualizadoEn": "2026-04-24T22:52:38.600Z"
        },
        {
          "id": "410928",
          "numero": "410928",
          "nombre": "Problemas de calidad de imagen en equipo de video",
          "estado": "en progreso",
          "creadoEn": "2026-04-24T22:51:00.901Z",
          "actualizaciones": [
            {
              "id": "modib48nlq4v8i6052b",
              "nota": "Se recibe el caso se solicitará a cliente mas información",
              "agente": "",
              "fecha": "2026-04-24T22:53:18.263Z",
              "estadoAnterior": "abierto",
              "estadoNuevo": "en progreso"
            },
            {
              "id": "1777071060901",
              "nota": "La imagen del equipo de video se ve borrosa durante las reuniones. El equipo ha revisado la cámara y no detecta problemas físicos, pero los participantes no pueden ver bien.",
              "agente": "Sistema",
              "fecha": "2026-04-24T22:51:00.901Z",
              "estadoAnterior": "",
              "estadoNuevo": ""
            }
          ],
          "actualizadoEn": "2026-04-24T22:53:18.263Z"
        }
      ],
      "creadoEn": "2026-04-22T19:22:00.305Z",
      "actualizadoEn": "2026-04-24T22:53:18.263Z",
      "updatedAt": "2026-04-24T15:25:40.417Z"
    },
    {
      "id": "mobnzjnv6b8wbvfolwh",
      "nombre": "Jose",
      "apellido": "Linero CollabMCR",
      "cargo": "CEO",
      "email": "jlinero@collab-col.wbx.ai",
      "email2": "",
      "telefono": "+576023981001",
      "empresa": "CollabMCR Technology Corporation",
      "dominioEmpresa": "collab-col.wbx.ai",
      "telEmpresa": "6052",
      "ciudad": "",
      "etapaVida": "cliente",
      "estadoLead": "En progreso",
      "propietarioContacto": "",
      "zonaHoraria": "America/Bogota",
      "objetivoMarketing": "",
      "presupuesto": "",
      "timeline": "",
      "notas": "",
      "actividades": [
        {
          "id": "1776984769024",
          "tipo": "whatsapp",
          "descripcion": "El cliente tiene interés en el servicio de Webex Contact Center",
          "asignadoA": "Oscar Piastri",
          "fecha": "2026-04-23T22:52:49.024Z"
        },
        {
          "id": "1776982078529",
          "tipo": "llamada",
          "descripcion": "El cliente tiene interés en el servicio de Webex Contact Center",
          "asignadoA": "Oscar Piastri",
          "fecha": "2026-04-23T22:07:58.529Z"
        }
      ],
      "deals": [],
      "tickets": [],
      "creadoEn": "2026-04-23T15:56:43.723Z",
      "actualizadoEn": "2026-04-23T22:52:49.024Z"
    },
    {
      "id": "moca7zhiaemq37wxhsp",
      "nombre": "Fernando",
      "apellido": "Alonso",
      "cargo": "Aston Marting F1 Driver",
      "email": "falonso@collab-col.wbx.ai",
      "email2": "",
      "telefono": "+14087215957",
      "empresa": "CollabMCR Technology Corporation",
      "dominioEmpresa": "collab-col.wbx.ai",
      "telEmpresa": "5957",
      "ciudad": "Bogotá, Colombia",
      "etapaVida": "cliente",
      "estadoLead": "Conectado",
      "propietarioContacto": "",
      "zonaHoraria": "America/Bogota",
      "objetivoMarketing": "",
      "presupuesto": "",
      "timeline": "",
      "notas": "",
      "actividades": [],
      "deals": [],
      "tickets": [],
      "creadoEn": "2026-04-24T02:19:09.030Z",
      "actualizadoEn": "2026-04-24T02:19:09.030Z"
    },
    {
      "id": "moca9homcbzjupb4f0n",
      "nombre": "Genny",
      "apellido": "Baron",
      "cargo": "Collaboration AE",
      "email": "genbaron@cisco.com",
      "email2": "",
      "telefono": "+573166904925",
      "empresa": "Cisco",
      "dominioEmpresa": "cisco.com",
      "telEmpresa": "",
      "ciudad": "",
      "etapaVida": "cliente",
      "estadoLead": "Nuevo",
      "propietarioContacto": "",
      "zonaHoraria": "America/Bogota",
      "objetivoMarketing": "",
      "presupuesto": "",
      "timeline": "",
      "notas": "",
      "actividades": [],
      "deals": [],
      "tickets": [],
      "creadoEn": "2026-04-24T02:20:19.270Z",
      "actualizadoEn": "2026-04-24T02:20:19.270Z"
    },
    {
      "id": "mocagoenpa1y7kiuko",
      "nombre": "Daniel",
      "apellido": "Tobar",
      "cargo": "Solutions Engineer",
      "email": "dtobar@cisco.com",
      "email2": "",
      "telefono": "+573132488767",
      "empresa": "Cisco",
      "dominioEmpresa": "cisco.com",
      "telEmpresa": "",
      "ciudad": "Bogotá, Colombia",
      "etapaVida": "cliente",
      "estadoLead": "Nuevo",
      "propietarioContacto": "",
      "zonaHoraria": "America/Bogota",
      "objetivoMarketing": "",
      "presupuesto": "",
      "timeline": "",
      "notas": "",
      "actividades": [],
      "deals": [],
      "tickets": [],
      "creadoEn": "2026-04-24T02:25:54.575Z",
      "actualizadoEn": "2026-04-24T02:25:54.575Z"
    },
    {
      "id": "mocai7bz315gaiwk2lj",
      "nombre": "Javier",
      "apellido": "Cuadros",
      "cargo": "Solutions Engineer",
      "email": "jcuadros@cisco.com",
      "email2": "",
      "telefono": "+573107741094",
      "empresa": "Cisco",
      "dominioEmpresa": "cisco.com",
      "telEmpresa": "",
      "ciudad": "Bogotá, Colombia",
      "etapaVida": "nuevo",
      "estadoLead": "Nuevo",
      "propietarioContacto": "",
      "zonaHoraria": "America/Bogota",
      "objetivoMarketing": "",
      "presupuesto": "",
      "timeline": "",
      "notas": "",
      "actividades": [],
      "deals": [],
      "tickets": [],
      "creadoEn": "2026-04-24T02:27:05.759Z",
      "actualizadoEn": "2026-04-24T02:27:05.759Z"
    }
  ]
}